dict_toolkit/__init__.py
dict_toolkit/__main__.py
dict_toolkit/dict_csv_handler.py
dict_toolkit/dict_handler.py
dict_toolkit/lexical_item.py
dict_toolkit/match_rules.py
dict_toolkit/core/__init__.py
dict_toolkit/core/dict_handler.py
dict_toolkit/core/lexical_item.py
dict_toolkit/core/match_rules.py
dict_toolkit/data/dict/split/A.csv
dict_toolkit/data/dict/split/B.csv
dict_toolkit/data/dict/split/C.csv
dict_toolkit/data/dict/split/D.csv
dict_toolkit/data/dict/split/E.csv
dict_toolkit/data/dict/split/F.csv
dict_toolkit/data/dict/split/G.csv
dict_toolkit/data/dict/split/H.csv
dict_toolkit/data/dict/split/I.csv
dict_toolkit/data/dict/split/J.csv
dict_toolkit/data/dict/split/K.csv
dict_toolkit/data/dict/split/L.csv
dict_toolkit/data/dict/split/M.csv
dict_toolkit/data/dict/split/N.csv
dict_toolkit/data/dict/split/O.csv
dict_toolkit/data/dict/split/P.csv
dict_toolkit/data/dict/split/Q.csv
dict_toolkit/data/dict/split/R.csv
dict_toolkit/data/dict/split/S.csv
dict_toolkit/data/dict/split/T.csv
dict_toolkit/data/dict/split/U.csv
dict_toolkit/data/dict/split/V.csv
dict_toolkit/data/dict/split/W.csv
dict_toolkit/data/dict/split/X.csv
dict_toolkit/data/dict/split/Y.csv
dict_toolkit/data/dict/split/Z.csv
dict_toolkit/extensions/__init__.py
dict_toolkit/extensions/dict_csv_handler.py
dict_toolkit/extensions/query_agent.py
dict_toolkit/utils/__init__.py
dict_toolkit/utils/csv_util.py
dict_toolkit-0.0.5.dist-info/METADATA
dict_toolkit-0.0.5.dist-info/WHEEL
dict_toolkit-0.0.5.dist-info/top_level.txt
dict_toolkit-0.0.5.dist-info/RECORD
