Metadata-Version: 2.1
Name: dict-toolkit
Version: 0.0.5
